{
  "version": "1.0",
  "timestamp": 1736186707088,
  "settings": {
    "gridSize": 100,
    "gridSpacing": 1,
    "playbackSpeed": 1000
  },
  "drones": {
    "MCU": {
      "color": "#70c172",
      "frames": [
        {"position": {"x": 0, "y": 0, "z": 2}, "heading": 0, "delay": 500},
        {"position": {"x": 0.5, "y": 1, "z": 2.5}, "heading": 45, "delay": 500},
        {"position": {"x": 1, "y": 0, "z": 3}, "heading": 0, "delay": 500},
        {"position": {"x": 1.5, "y": -1, "z": 2.5}, "heading": -45, "delay": 500},
        {"position": {"x": 2, "y": 0, "z": 2}, "heading": 0, "delay": 500},
        {"position": {"x": 2.5, "y": 1, "z": 2.5}, "heading": 45, "delay": 500},
        {"position": {"x": 3, "y": 0, "z": 3}, "heading": 0, "delay": 500},
        {"position": {"x": 3.5, "y": -1, "z": 2.5}, "heading": -45, "delay": 500},
        {"position": {"x": 4, "y": 0, "z": 2}, "heading": 0, "delay": 500},
        {"position": {"x": 4.5, "y": 1, "z": 2.5}, "heading": 45, "delay": 500},
        {"position": {"x": 5, "y": 0, "z": 3}, "heading": 0, "delay": 500},
        {"position": {"x": 5.5, "y": -1, "z": 2.5}, "heading": -45, "delay": 500},
        {"position": {"x": 6, "y": 0, "z": 2}, "heading": 0, "delay": 500},
        {"position": {"x": 6.5, "y": 1, "z": 2.5}, "heading": 45, "delay": 500},
        {"position": {"x": 7, "y": 0, "z": 3}, "heading": 0, "delay": 500},
        {"position": {"x": 6.5, "y": -1, "z": 2.5}, "heading": -45, "delay": 500},
        {"position": {"x": 6, "y": 0, "z": 2}, "heading": 180, "delay": 500},
        {"position": {"x": 5.5, "y": 1, "z": 2.5}, "heading": 135, "delay": 500},
        {"position": {"x": 5, "y": 0, "z": 3}, "heading": 180, "delay": 500},
        {"position": {"x": 4.5, "y": -1, "z": 2.5}, "heading": 225, "delay": 500},
        {"position": {"x": 4, "y": 0, "z": 2}, "heading": 180, "delay": 500},
        {"position": {"x": 3.5, "y": 1, "z": 2.5}, "heading": 135, "delay": 500},
        {"position": {"x": 3, "y": 0, "z": 3}, "heading": 180, "delay": 500},
        {"position": {"x": 2.5, "y": -1, "z": 2.5}, "heading": 225, "delay": 500},
        {"position": {"x": 2, "y": 0, "z": 2}, "heading": 180, "delay": 500},
        {"position": {"x": 1.5, "y": 1, "z": 2.5}, "heading": 135, "delay": 500},
        {"position": {"x": 1, "y": 0, "z": 3}, "heading": 180, "delay": 500},
        {"position": {"x": 0.5, "y": -1, "z": 2.5}, "heading": 225, "delay": 500},
        {"position": {"x": 0, "y": 0, "z": 2}, "heading": 180, "delay": 500},
        {"position": {"x": 0, "y": 0, "z": 2}, "heading": 0, "delay": 500}
      ]
    },
    "CD1": {
      "color": "#2c7bf2",
      "frames": [
        {"position": {"x": -1, "y": 0, "z": 2}, "heading": 0, "delay": 500},
        {"position": {"x": -0.5, "y": 1, "z": 2.5}, "heading": 45, "delay": 500},
        {"position": {"x": 0, "y": 0, "z": 3}, "heading": 0, "delay": 500},
        {"position": {"x": 0.5, "y": -1, "z": 2.5}, "heading": -45, "delay": 500},
        {"position": {"x": 1, "y": 0, "z": 2}, "heading": 0, "delay": 500},
        {"position": {"x": 1.5, "y": 1, "z": 2.5}, "heading": 45, "delay": 500},
        {"position": {"x": 2, "y": 0, "z": 3}, "heading": 0, "delay": 500},
        {"position": {"x": 2.5, "y": -1, "z": 2.5}, "heading": -45, "delay": 500},
        {"position": {"x": 3, "y": 0, "z": 2}, "heading": 0, "delay": 500},
        {"position": {"x": 3.5, "y": 1, "z": 2.5}, "heading": 45, "delay": 500},
        {"position": {"x": 4, "y": 0, "z": 3}, "heading": 0, "delay": 500},
        {"position": {"x": 4.5, "y": -1, "z": 2.5}, "heading": -45, "delay": 500},
        {"position": {"x": 5, "y": 0, "z": 2}, "heading": 0, "delay": 500},
        {"position": {"x": 5.5, "y": 1, "z": 2.5}, "heading": 45, "delay": 500},
        {"position": {"x": 6, "y": 0, "z": 3}, "heading": 0, "delay": 500},
        {"position": {"x": 5.5, "y": -1, "z": 2.5}, "heading": -45, "delay": 500},
        {"position": {"x": 5, "y": 0, "z": 2}, "heading": 180, "delay": 500},
        {"position": {"x": 4.5, "y": 1, "z": 2.5}, "heading": 135, "delay": 500},
        {"position": {"x": 4, "y": 0, "z": 3}, "heading": 180, "delay": 500},
        {"position": {"x": 3.5, "y": -1, "z": 2.5}, "heading": 225, "delay": 500},
        {"position": {"x": 3, "y": 0, "z": 2}, "heading": 180, "delay": 500},
        {"position": {"x": 2.5, "y": 1, "z": 2.5}, "heading": 135, "delay": 500},
        {"position": {"x": 2, "y": 0, "z": 3}, "heading": 180, "delay": 500},
        {"position": {"x": 1.5, "y": -1, "z": 2.5}, "heading": 225, "delay": 500},
        {"position": {"x": 1, "y": 0, "z": 2}, "heading": 180, "delay": 500},
        {"position": {"x": 0.5, "y": 1, "z": 2.5}, "heading": 135, "delay": 500},
        {"position": {"x": 0, "y": 0, "z": 3}, "heading": 180, "delay": 500},
        {"position": {"x": -0.5, "y": -1, "z": 2.5}, "heading": 225, "delay": 500},
        {"position": {"x": -1, "y": 0, "z": 2}, "heading": 180, "delay": 500},
        {"position": {"x": -1, "y": 0, "z": 2}, "heading": 0, "delay": 500}
      ]
    },
    "CD2": {
      "color": "#f05151",
      "frames": [
        {"position": {"x": -2, "y": 0, "z": 2}, "heading": 0, "delay": 500},
        {"position": {"x": -1.5, "y": 1, "z": 2.5}, "heading": 45, "delay": 500},
        {"position": {"x": -1, "y": 0, "z": 3}, "heading": 0, "delay": 500},
        {"position": {"x": -0.5, "y": -1, "z": 2.5}, "heading": -45, "delay": 500},
        {"position": {"x": 0, "y": 0, "z": 2}, "heading": 0, "delay": 500},
        {"position": {"x": 0.5, "y": 1, "z": 2.5}, "heading": 45, "delay": 500},
        {"position": {"x": 1, "y": 0, "z": 3}, "heading": 0, "delay": 500},
        {"position": {"x": 1.5, "y": -1, "z": 2.5}, "heading": -45, "delay": 500},
        {"position": {"x": 2, "y": 0, "z": 2}, "heading": 0, "delay": 500},
        {"position": {"x": 2.5, "y": 1, "z": 2.5}, "heading": 45, "delay": 500},
        {"position": {"x": 3, "y": 0, "z": 3}, "heading": 0, "delay": 500},
        {"position": {"x": 3.5, "y": -1, "z": 2.5}, "heading": -45, "delay": 500},
        {"position": {"x": 4, "y": 0, "z": 2}, "heading": 0, "delay": 500},
        {"position": {"x": 4.5, "y": 1, "z": 2.5}, "heading": 45, "delay": 500},
        {"position": {"x": 5, "y": 0, "z": 3}, "heading": 0, "delay": 500},
        {"position": {"x": 4.5, "y": -1, "z": 2.5}, "heading": -45, "delay": 500},
        {"position": {"x": 4, "y": 0, "z": 2}, "heading": 180, "delay": 500},
        {"position": {"x": 3.5, "y": 1, "z": 2.5}, "heading": 135, "delay": 500},
        {"position": {"x": 3, "y": 0, "z": 3}, "heading": 180, "delay": 500},
        {"position": {"x": 2.5, "y": -1, "z": 2.5}, "heading": 225, "delay": 500},
        {"position": {"x": 2, "y": 0, "z": 2}, "heading": 180, "delay": 500},
        {"position": {"x": 1.5, "y": 1, "z": 2.5}, "heading": 135, "delay": 500},
        {"position": {"x": 1, "y": 0, "z": 3}, "heading": 180, "delay": 500},
        {"position": {"x": 0.5, "y": -1, "z": 2.5}, "heading": 225, "delay": 500},
        {"position": {"x": 0, "y": 0, "z": 2}, "heading": 180, "delay": 500},
        {"position": {"x": -0.5, "y": 1, "z": 2.5}, "heading": 135, "delay": 500},
        {"position": {"x": -1, "y": 0, "z": 3}, "heading": 180, "delay": 500},
        {"position": {"x": -1.5, "y": -1, "z": 2.5}, "heading": 225, "delay": 500},
        {"position": {"x": -2, "y": 0, "z": 2}, "heading": 180, "delay": 500},
        {"position": {"x": -2, "y": 0, "z": 2}, "heading": 0, "delay": 500}
      ]
    },
    "CD3": {
      "color": "#ffab49",
      "frames": [
        {"position": {"x": -3, "y": 0, "z": 2}, "heading": 0, "delay": 500},
        {"position": {"x": -2.5, "y": 1, "z": 2.5}, "heading": 45, "delay": 500},
        {"position": {"x": -2, "y": 0, "z": 3}, "heading": 0, "delay": 500},
        {"position": {"x": -1.5, "y": -1, "z": 2.5}, "heading": -45, "delay": 500},
        {"position": {"x": -1, "y": 0, "z": 2}, "heading": 0, "delay": 500},
        {"position": {"x": -0.5, "y": 1, "z": 2.5}, "heading": 45, "delay": 500},
        {"position": {"x": 0, "y": 0, "z": 3}, "heading": 0, "delay": 500},
        {"position": {"x": 0.5, "y": -1, "z": 2.5}, "heading": -45, "delay": 500},
        {"position": {"x": 1, "y": 0, "z": 2}, "heading": 0, "delay": 500},
        {"position": {"x": 1.5, "y": 1, "z": 2.5}, "heading": 45, "delay": 500},
        {"position": {"x": 2, "y": 0, "z": 3}, "heading": 0, "delay": 500},
        {"position": {"x": 2.5, "y": -1, "z": 2.5}, "heading": -45, "delay": 500},
        {"position": {"x": 3, "y": 0, "z": 2}, "heading": 0, "delay": 500},
        {"position": {"x": 3.5, "y": 1, "z": 2.5}, "heading": 45, "delay": 500},
        {"position": {"x": 4, "y": 0, "z": 3}, "heading": 0, "delay": 500},
        {"position": {"x": 3.5, "y": -1, "z": 2.5}, "heading": -45, "delay": 500},
        {"position": {"x": 3, "y": 0, "z": 2}, "heading": 180, "delay": 500},
        {"position": {"x": 2.5, "y": 1, "z": 2.5}, "heading": 135, "delay": 500},
        {"position": {"x": 2, "y": 0, "z": 3}, "heading": 180, "delay": 500},
        {"position": {"x": 1.5, "y": -1, "z": 2.5}, "heading": 225, "delay": 500},
        {"position": {"x": 1, "y": 0, "z": 2}, "heading": 180, "delay": 500},
        {"position": {"x": 0.5, "y": 1, "z": 2.5}, "heading": 135, "delay": 500},
        {"position": {"x": 0, "y": 0, "z": 3}, "heading": 180, "delay": 500},
        {"position": {"x": -0.5, "y": -1, "z": 2.5}, "heading": 225, "delay": 500},
        {"position": {"x": -1, "y": 0, "z": 2}, "heading": 180, "delay": 500},
        {"position": {"x": -1.5, "y": 1, "z": 2.5}, "heading": 135, "delay": 500},
        {"position": {"x": -2, "y": 0, "z": 3}, "heading": 180, "delay": 500},
        {"position": {"x": -2.5, "y": -1, "z": 2.5}, "heading": 225, "delay": 500},
        {"position": {"x": -3, "y": 0, "z": 2}, "heading": 180, "delay": 500},
        {"position": {"x": -3, "y": 0, "z": 2}, "heading": 0, "delay": 500}
      ]
    },
    "CD4": {
      "color": "#9c27b0",
      "frames": [
        {"position": {"x": -4, "y": 0, "z": 2}, "heading": 0, "delay": 500},
        {"position": {"x": -3.5, "y": 1, "z": 2.5}, "heading": 45, "delay": 500},
        {"position": {"x": -3, "y": 0, "z": 3}, "heading": 0, "delay": 500},
        {"position": {"x": -2.5, "y": -1, "z": 2.5}, "heading": -45, "delay": 500},
        {"position": {"x": -2, "y": 0, "z": 2}, "heading": 0, "delay": 500},
        {"position": {"x": -1.5, "y": 1, "z": 2.5}, "heading": 45, "delay": 500},
        {"position": {"x": -1, "y": 0, "z": 3}, "heading": 0, "delay": 500},
        {"position": {"x": -0.5, "y": -1, "z": 2.5}, "heading": -45, "delay": 500},
        {"position": {"x": 0, "y": 0, "z": 2}, "heading": 0, "delay": 500},
        {"position": {"x": 0.5, "y": 1, "z": 2.5}, "heading": 45, "delay": 500},
        {"position": {"x": 1, "y": 0, "z": 3}, "heading": 0, "delay": 500},
        {"position": {"x": 1.5, "y": -1, "z": 2.5}, "heading": -45, "delay": 500},
        {"position": {"x": 2, "y": 0, "z": 2}, "heading": 0, "delay": 500},
        {"position": {"x": 2.5, "y": 1, "z": 2.5}, "heading": 45, "delay": 500},
        {"position": {"x": 3, "y": 0, "z": 3}, "heading": 0, "delay": 500},
        {"position": {"x": 2.5, "y": -1, "z": 2.5}, "heading": -45, "delay": 500},
        {"position": {"x": 2, "y": 0, "z": 2}, "heading": 180, "delay": 500},
        {"position": {"x": 1.5, "y": 1, "z": 2.5}, "heading": 135, "delay": 500},
        {"position": {"x": 1, "y": 0, "z": 3}, "heading": 180, "delay": 500},
        {"position": {"x": 0.5, "y": -1, "z": 2.5}, "heading": 225, "delay": 500},
        {"position": {"x": 0, "y": 0, "z": 2}, "heading": 180, "delay": 500},
        {"position": {"x": -0.5, "y": 1, "z": 2.5}, "heading": 135, "delay": 500},
        {"position": {"x": -1, "y": 0, "z": 3}, "heading": 180, "delay": 500},
        {"position": {"x": -1.5, "y": -1, "z": 2.5}, "heading": 225, "delay": 500},
        {"position": {"x": -2, "y": 0, "z": 2}, "heading": 180, "delay": 500},
        {"position": {"x": -2.5, "y": 1, "z": 2.5}, "heading": 135, "delay": 500},
        {"position": {"x": -3, "y": 0, "z": 3}, "heading": 180, "delay": 500},
        {"position": {"x": -3.5, "y": -1, "z": 2.5}, "heading": 225, "delay": 500},
        {"position": {"x": -4, "y": 0, "z": 2}, "heading": 180, "delay": 500},
        {"position": {"x": -4, "y": 0, "z": 2}, "heading": 0, "delay": 500}
      ]
    }
  }
} 